msbff/__init__.py
msbff/default.py
msbff/msbff_pipeline.py
msbff/preprocessing.py
msbff/processing.py
msbff/visualization.py
msbff-0.0.5.data/scripts/msbff
msbff-0.0.5.dist-info/LICENSE
msbff-0.0.5.dist-info/METADATA
msbff-0.0.5.dist-info/WHEEL
msbff-0.0.5.dist-info/top_level.txt
msbff-0.0.5.dist-info/RECORD
