Metadata-Version: 2.1
Name: msbff
Version: 0.0.5
Summary: Bioactive Fractions Filtering.
Home-page: https://github.com/BioGavin/msbff
Author: Zhen-Yi Zhou
Author-email: gavinchou64@gmail.com
License: GPL
Classifier: Programming Language :: Python :: 3.8
Classifier: License :: OSI Approved :: GNU General Public License v3 (GPLv3)
Classifier: Operating System :: OS Independent
Requires-Python: >=3.8
License-File: LICENSE
Requires-Dist: pandas
Requires-Dist: matplotlib
Requires-Dist: numpy
